airflow_trigger_multiple_dag_run/__init__.py
airflow_trigger_multiple_dag_run/exceptions.py
airflow_trigger_multiple_dag_run/models.py
airflow_trigger_multiple_dag_run/operators.py
airflow_trigger_multiple_dag_run/sensors.py
airflow_trigger_multiple_dag_run-1.0.0.dist-info/LICENSE
airflow_trigger_multiple_dag_run-1.0.0.dist-info/METADATA
airflow_trigger_multiple_dag_run-1.0.0.dist-info/WHEEL
airflow_trigger_multiple_dag_run-1.0.0.dist-info/RECORD
