Metadata-Version: 2.1
Name: airflow-trigger-multiple-dag-run
Version: 1.0.0
Summary: Plugin to trigger and monitor multiple dag runs
License: MIT
Author: Jaya Bharath
Author-email: bharath21196@gmail.com
Requires-Python: >=3.7.13,<4.0.0
Classifier: License :: OSI Approved :: MIT License
Classifier: Programming Language :: Python :: 3
Classifier: Programming Language :: Python :: 3.8
Classifier: Programming Language :: Python :: 3.9
Classifier: Programming Language :: Python :: 3.10
Classifier: Programming Language :: Python :: 3.11
Requires-Dist: apache-airflow (>=2.6.3,<3.0.0)
